LICENSE
README.md
setup.py
micropython_plc.egg-info/PKG-INFO
micropython_plc.egg-info/SOURCES.txt
micropython_plc.egg-info/dependency_links.txt
micropython_plc.egg-info/top_level.txt
plc/__init__.py
plc/drivers/__init__.py
plc/drivers/i2cexpander.py
plc/drivers/octopus_plcshield.py
plc/elements/__init__.py
plc/elements/rs.py
plc/elements/rs_pulse.py
plc/elements/timers/__init__.py
plc/elements/timers/rto.py
plc/elements/timers/tof.py
plc/elements/timers/ton.py
plc/inputs/__init__.py
plc/inputs/virtual.py
plc/operands/__init__.py
plc/operands/op_and.py
plc/operands/op_not.py
plc/operands/op_or.py
plc/outputs/__init__.py
plc/outputs/virtual.py