Metadata-Version: 2.1
Name: micropython-plc
Version: 0.0.1
Summary: PLC library for micropython
Home-page: https://github.com/octopuslab-cz/micropython-plc
Author: Petr Kracik
Author-email: petrkr@petrkr.net
License: MIT
Platform: UNKNOWN
Classifier: Programming Language :: Python :: 3
Classifier: License :: OSI Approved :: MIT License
Classifier: Operating System :: OS Independent
Classifier: Development Status :: 3 - Alpha
Requires-Python: >=3.4
License-File: LICENSE
